polyaxon_client/__init__.py
polyaxon_client/api_config.py
polyaxon_client/client.py
polyaxon_client/exceptions.py
polyaxon_client/logger.py
polyaxon_client/settings.py
polyaxon_client/utils.py
polyaxon_client/api/__init__.py
polyaxon_client/api/auth.py
polyaxon_client/api/base.py
polyaxon_client/api/bookmark.py
polyaxon_client/api/build_job.py
polyaxon_client/api/cluster.py
polyaxon_client/api/data.py
polyaxon_client/api/experiment.py
polyaxon_client/api/experiment_group.py
polyaxon_client/api/experiment_job.py
polyaxon_client/api/job.py
polyaxon_client/api/project.py
polyaxon_client/api/user.py
polyaxon_client/api/version.py
polyaxon_client/handlers/__init__.py
polyaxon_client/handlers/conf.py
polyaxon_client/handlers/handler.py
polyaxon_client/models/__init__.py
polyaxon_client/schemas/__init__.py
polyaxon_client/tracking/__init__.py
polyaxon_client/tracking/base.py
polyaxon_client/tracking/build.py
polyaxon_client/tracking/experiment.py
polyaxon_client/tracking/group.py
polyaxon_client/tracking/is_managed.py
polyaxon_client/tracking/job.py
polyaxon_client/tracking/no_op.py
polyaxon_client/tracking/offline.py
polyaxon_client/tracking/paths.py
polyaxon_client/tracking/contrib/__init__.py
polyaxon_client/tracking/contrib/fastai.py
polyaxon_client/tracking/contrib/keras.py
polyaxon_client/tracking/contrib/logging_tensor_hook.py
polyaxon_client/tracking/utils/__init__.py
polyaxon_client/tracking/utils/backend.py
polyaxon_client/tracking/utils/cmd.py
polyaxon_client/tracking/utils/code_reference.py
polyaxon_client/tracking/utils/env.py
polyaxon_client/tracking/utils/hashing.py
polyaxon_client/tracking/utils/project.py
polyaxon_client/tracking/utils/tags.py
polyaxon_client/transport/__init__.py
polyaxon_client/transport/http_transport.py
polyaxon_client/transport/periodic_transport.py
polyaxon_client/transport/retry_transport.py
polyaxon_client/transport/socket_transport.py
polyaxon_client/transport/threaded_transport.py
polyaxon_client/transport/utils.py
polyaxon_client-0.6.1.dist-info/LICENSE
polyaxon_client-0.6.1.dist-info/METADATA
polyaxon_client-0.6.1.dist-info/WHEEL
polyaxon_client-0.6.1.dist-info/top_level.txt
polyaxon_client-0.6.1.dist-info/RECORD
