Metadata-Version: 2.1
Name: polyaxon-client
Version: 0.6.1
Summary: Python client to interact with Polyaxon API.
Home-page: https://github.com/polyaxon/polyaxon-client
Author: Mourad Mourafiq
Author-email: mourad@polyaxon.com
Maintainer: Mourad Mourafiq
Maintainer-email: mourad@polyaxon.com
License: MIT
Keywords: polyaxon,aws,s3,microsoft,azure,google cloud storage,gcs,tensorFlow,deep-learning,machine-learning,data-science,neural-networks,artificial-intelligence,ai,reinforcement-learning,kubernetes
Platform: any
Classifier: Programming Language :: Python
Classifier: Programming Language :: Python :: 2
Classifier: Programming Language :: Python :: 2.7
Classifier: Programming Language :: Python :: 3
Classifier: Programming Language :: Python :: 3.5
Classifier: Programming Language :: Python :: 3.6
Classifier: Programming Language :: Python :: 3.7
Classifier: Operating System :: OS Independent
Classifier: Intended Audience :: Developers
Classifier: Intended Audience :: Science/Research
Classifier: Topic :: Scientific/Engineering :: Artificial Intelligence
Requires-Python: >=2.7, !=3.0.*, !=3.1.*, !=3.2.*, !=3.3.*, !=3.4.*
Requires-Dist: polyaxon-schemas (==0.6.1)
Requires-Dist: polystores (>=0.2.4)
Requires-Dist: psutil (>=5.4.7)
Requires-Dist: requests (>=2.20.0)
Requires-Dist: requests-toolbelt (>=0.8.0)
Requires-Dist: websocket-client (>=0.53.0)
Provides-Extra: azure
Requires-Dist: azure-storage ; extra == 'azure'
Provides-Extra: gcs
Requires-Dist: google-cloud-storage ; extra == 'gcs'
Provides-Extra: s3
Requires-Dist: boto3 ; extra == 's3'
Requires-Dist: botocore ; extra == 's3'
